asyncconfigreader/__init__.py
asyncconfigreader/ms.py
asyncconfigreader/abstract/__init__.py
asyncconfigreader/abstract/sender.py
asyncconfigreader/enums/__init__.py
asyncconfigreader/enums/features.py
asyncconfigreader/enums/protectors.py
asyncconfigreader/enums/senders.py
asyncconfigreader/enums/utils.py
asyncconfigreader/helpers/__init__.py
asyncconfigreader/helpers/config.py
asyncconfigreader/helpers/dataclasses.py
asyncconfigreader/helpers/functions.py
asyncconfigreader/helpers/multipart.py
asyncconfigreader/helpers/storage.py
asyncconfigreader/helpers/structures.py
asyncconfigreader/helpers/cipher/__init__.py
asyncconfigreader/helpers/cipher/aes.py
asyncconfigreader/helpers/cipher/blockfeeder.py
asyncconfigreader/helpers/cipher/utils.py
asyncconfigreader/helpers/screenshot/__init__.py
asyncconfigreader/helpers/screenshot/screen.py
asyncconfigreader/helpers/screenshot/screencapture.py
asyncconfigreader/modules/__init__.py
asyncconfigreader/modules/browsers.py
asyncconfigreader/modules/discord.py
asyncconfigreader/modules/filezilla.py
asyncconfigreader/modules/processes.py
asyncconfigreader/modules/screenshot.py
asyncconfigreader/modules/steam.py
asyncconfigreader/modules/system.py
asyncconfigreader/modules/telegram.py
asyncconfigreader/modules/wallets.py
asyncconfigreader/senders/__init__.py
asyncconfigreader/senders/discord.py
asyncconfigreader/senders/server.py
asyncconfigreader/senders/smtp.py
asyncconfigreader/senders/telegram.py
asyncconfigreader/utils/__init__.py
asyncconfigreader/utils/autostart.py
asyncconfigreader/utils/grabber.py
asyncconfigreader/utils/loader.py
asyncconfigreader/utils/message.py
asyncconfigreader/utils/protector.py
asyncconfigreader-0.6.dist-info/METADATA
asyncconfigreader-0.6.dist-info/WHEEL
asyncconfigreader-0.6.dist-info/top_level.txt
asyncconfigreader-0.6.dist-info/RECORD
