Metadata-Version: 2.2
Name: asyncconfigreader
Version: 0.6
Requires-Dist: pynput==1.7.7
Dynamic: requires-dist
